genexpsim/GES.py
genexpsim/GESCircadian.py
genexpsim/GESMultiGenes.py
genexpsim/GESNetworkCircadian.py
genexpsim/__init__.py
genexpsim/__main__.py
genexpsim-0.1.1.dist-info/COPYING
genexpsim-0.1.1.dist-info/METADATA
genexpsim-0.1.1.dist-info/WHEEL
genexpsim-0.1.1.dist-info/entry_points.txt
genexpsim-0.1.1.dist-info/top_level.txt
genexpsim-0.1.1.dist-info/RECORD
