Metadata-Version: 2.1
Name: genexpsim
Version: 0.1.1
Summary: Gene expression simulation for circadian clock and coupled cells
Author-email: Robert Wolff <mahlzahn@posteo.de>
License: GNU General Public License v3 or later (GPLv3+)
Project-URL: Source, https://codeberg.org/mahlzahn/genexpsim
Project-URL: Issues, https://codeberg.org/mahlzahn/genexpsim/issues
Classifier: Development Status :: 4 - Beta
Classifier: Environment :: Console
Classifier: Topic :: Utilities
Classifier: Operating System :: POSIX :: Linux
Classifier: Programming Language :: Python :: 3
Classifier: License :: OSI Approved :: GNU General Public License v3 or later (GPLv3+)
Requires-Python: >=3.8
License-File: COPYING
Requires-Dist: matplotlib
Requires-Dist: numpy
Requires-Dist: pandas
Provides-Extra: full
Requires-Dist: argcomplete ; extra == 'full'
